smokey/__init__.py
smokey/_version.py
smokey-0.1.dist-info/DESCRIPTION.rst
smokey-0.1.dist-info/METADATA
smokey-0.1.dist-info/RECORD
smokey-0.1.dist-info/WHEEL
smokey-0.1.dist-info/metadata.json
smokey-0.1.dist-info/top_level.txt
